correl/plotting.py
correl/w2dyn_post.py
correl/hubbard.py
correl/__init__.py
correl/pseudogap.py
correl/_fast_bubble.cpython-39-x86_64-linux-gnu.so
correl-0.1.22.dist-info/METADATA
correl-0.1.22.dist-info/RECORD
correl-0.1.22.dist-info/WHEEL
correl-0.1.22.dist-info/licenses/LICENSE
