Metadata-Version: 2.1
Name: correl
Version: 0.1.22
Summary: Library for w2dynamics (DMFT) postprocessing and for solving correlated electron problems.
Author-Email: Matthias Reitner <matthias.reitner@tuwien.ac.at>, Emin Moghadas <emin.moghadas@tuwien.ac.at>
Maintainer-Email: Matthias Reitner <matthias.reitner@tuwien.ac.at>, Emin Moghadas <emin.moghadas@tuwien.ac.at>
Classifier: Programming Language :: Python :: 3
Classifier: License :: OSI Approved :: MIT License
Classifier: Operating System :: OS Independent
Requires-Python: >=3.8
Requires-Dist: numpy
Requires-Dist: matplotlib
Requires-Dist: scipy
Requires-Dist: h5py
Requires-Dist: pytest; extra == "tests"
Requires-Dist: pytest-cov; extra == "tests"
Provides-Extra: tests
